<?xml version="1.0" encoding="UTF-8"?>
<MF0 version="1.1" packageUris="http://schema.mathworks.com/mf0/ci/19700101 http://schema.mathworks.com/mf0/sl_modelref_info/R2022b http://schema.mathworks.com/mf0/slexec_mm_sto/R2022b_202202091112 http://schema.mathworks.com/mf0/sltp_mm/R2022b_202203181029">
  <ModelRefInfoRepo.ModelRefInfoRoot type="ModelRefInfoRepo.ModelRefInfoRoot" uuid="11c2a55d-a49a-41ee-b4ea-58f412a50ec0">
    <childModelRefInfo type="ModelRefInfoRepo.ChildModelRefInfo" uuid="2fe1d709-24f5-4882-9fd9-1df33524459e">
      <modelName>CPS_Eva</modelName>
      <modelPath>CPS_Eva</modelPath>
    </childModelRefInfo>
    <dataTransferInfos>AAFJTQAAAAAOAAAAOAAAAAYAAAAIAAAAAgAAAAAAAAAFAAAACAAAAAAAAAABAAAAAQAAAAAAAAAFAAQAAQAAAAEAAAAAAAAA</dataTransferInfos>
    <defaultsCMapping>{&quot;Inports&quot;:&quot;{\&quot;Name\&quot;:\&quot;Default\&quot;,\&quot;Checksum\&quot;:\&quot;Default\&quot;,\&quot;PerInstancePropertiesChecksum\&quot;:\&quot;\&quot;,\&quot;MemorySectionName\&quot;:\&quot;\&quot;,\&quot;MemorySectionChecksum\&quot;:\&quot;\&quot;}&quot;,&quot;Outports&quot;:&quot;{\&quot;Name\&quot;:\&quot;Default\&quot;,\&quot;Checksum\&quot;:\&quot;Default\&quot;,\&quot;PerInstancePropertiesChecksum\&quot;:\&quot;\&quot;,\&quot;MemorySectionName\&quot;:\&quot;\&quot;,\&quot;MemorySectionChecksum\&quot;:\&quot;\&quot;}&quot;,&quot;ParameterArguments&quot;:&quot;{\&quot;Name\&quot;:\&quot;Default\&quot;,\&quot;Checksum\&quot;:\&quot;Default\&quot;,\&quot;PerInstancePropertiesChecksum\&quot;:\&quot;\&quot;,\&quot;MemorySectionName\&quot;:\&quot;None\&quot;,\&quot;MemorySectionChecksum\&quot;:\&quot;None\&quot;}&quot;,&quot;LocalParameters&quot;:&quot;{\&quot;Name\&quot;:\&quot;Default\&quot;,\&quot;Checksum\&quot;:\&quot;Default\&quot;,\&quot;PerInstancePropertiesChecksum\&quot;:\&quot;\&quot;,\&quot;MemorySectionName\&quot;:\&quot;\&quot;,\&quot;MemorySectionChecksum\&quot;:\&quot;\&quot;}&quot;,&quot;GlobalParameters&quot;:&quot;{\&quot;Name\&quot;:\&quot;Default\&quot;,\&quot;Checksum\&quot;:\&quot;Default\&quot;,\&quot;PerInstancePropertiesChecksum\&quot;:\&quot;\&quot;,\&quot;MemorySectionName\&quot;:\&quot;\&quot;,\&quot;MemorySectionChecksum\&quot;:\&quot;\&quot;}&quot;,&quot;InternalData&quot;:&quot;{\&quot;Name\&quot;:\&quot;Default\&quot;,\&quot;Checksum\&quot;:\&quot;Default\&quot;,\&quot;PerInstancePropertiesChecksum\&quot;:\&quot;\&quot;,\&quot;MemorySectionName\&quot;:\&quot;\&quot;,\&quot;MemorySectionChecksum\&quot;:\&quot;\&quot;}&quot;,&quot;SharedLocalDataStores&quot;:&quot;{\&quot;Name\&quot;:\&quot;Default\&quot;,\&quot;Checksum\&quot;:\&quot;Default\&quot;,\&quot;PerInstancePropertiesChecksum\&quot;:\&quot;\&quot;,\&quot;MemorySectionName\&quot;:\&quot;None\&quot;,\&quot;MemorySectionChecksum\&quot;:\&quot;None\&quot;}&quot;,&quot;GlobalDataStores&quot;:&quot;{\&quot;Name\&quot;:\&quot;Default\&quot;,\&quot;Checksum\&quot;:\&quot;Default\&quot;,\&quot;PerInstancePropertiesChecksum\&quot;:\&quot;\&quot;,\&quot;MemorySectionName\&quot;:\&quot;None\&quot;,\&quot;MemorySectionChecksum\&quot;:\&quot;None\&quot;}&quot;,&quot;Constants&quot;:&quot;{\&quot;Name\&quot;:\&quot;Default\&quot;,\&quot;Checksum\&quot;:\&quot;Default\&quot;,\&quot;PerInstancePropertiesChecksum\&quot;:\&quot;\&quot;,\&quot;MemorySectionName\&quot;:\&quot;\&quot;,\&quot;MemorySectionChecksum\&quot;:\&quot;\&quot;}&quot;,&quot;DataTransfers&quot;:&quot;{\&quot;Name\&quot;:\&quot;Default\&quot;,\&quot;Checksum\&quot;:\&quot;Default\&quot;,\&quot;PerInstancePropertiesChecksum\&quot;:\&quot;\&quot;,\&quot;MemorySectionName\&quot;:\&quot;None\&quot;,\&quot;MemorySectionChecksum\&quot;:\&quot;None\&quot;}&quot;,&quot;ModelData&quot;:&quot;{\&quot;Name\&quot;:\&quot;Default\&quot;,\&quot;Checksum\&quot;:\&quot;Default\&quot;,\&quot;PerInstancePropertiesChecksum\&quot;:\&quot;\&quot;,\&quot;MemorySectionName\&quot;:\&quot;None\&quot;,\&quot;MemorySectionChecksum\&quot;:\&quot;None\&quot;}&quot;,&quot;InitializeTerminate&quot;:&quot;{\&quot;Name\&quot;:\&quot;Default\&quot;,\&quot;Checksum\&quot;:\&quot;Default\&quot;,\&quot;PerInstancePropertiesChecksum\&quot;:\&quot;\&quot;,\&quot;MemorySectionName\&quot;:\&quot;\&quot;,\&quot;MemorySectionChecksum\&quot;:\&quot;\&quot;}&quot;,&quot;Execution&quot;:&quot;{\&quot;Name\&quot;:\&quot;Default\&quot;,\&quot;Checksum\&quot;:\&quot;Default\&quot;,\&quot;PerInstancePropertiesChecksum\&quot;:\&quot;\&quot;,\&quot;MemorySectionName\&quot;:\&quot;\&quot;,\&quot;MemorySectionChecksum\&quot;:\&quot;\&quot;}&quot;,&quot;SharedUtility&quot;:&quot;{\&quot;Name\&quot;:\&quot;Default\&quot;,\&quot;Checksum\&quot;:\&quot;Default\&quot;,\&quot;PerInstancePropertiesChecksum\&quot;:\&quot;\&quot;,\&quot;MemorySectionName\&quot;:\&quot;\&quot;,\&quot;MemorySectionChecksum\&quot;:\&quot;\&quot;}&quot;}</defaultsCMapping>
    <globalVariables>Gromit_Cal_tranp</globalVariables>
    <globalVariables>M</globalVariables>
    <globalVariables>T</globalVariables>
    <globalVariables>c</globalVariables>
    <globalVariables>duration_sim</globalVariables>
    <globalVariables>k</globalVariables>
    <globalVariables>start_position_cm</globalVariables>
    <globalVariables>tare</globalVariables>
    <hasBlockWithPeriodicDiscreteSampleTime>true</hasBlockWithPeriodicDiscreteSampleTime>
    <hasBwsAccessed>true</hasBwsAccessed>
    <hasBwsAccessedByAnyModel>true</hasBwsAccessedByAnyModel>
    <hasContinuousSampleTime>true</hasContinuousSampleTime>
    <hasNoncontSigFeedingDerivPorts>true</hasNoncontSigFeedingDerivPorts>
    <isBdInSimModeForSimCodegenVariants>false</isBdInSimModeForSimCodegenVariants>
    <loggingSaveFormat>2</loggingSaveFormat>
    <massMatrixNzMax>4</massMatrixNzMax>
    <maxFreqHz>-1.0</maxFreqHz>
    <nonTunableVariables>T</nonTunableVariables>
    <numCStateRecs>1</numCStateRecs>
    <numContinuousStates>4</numContinuousStates>
    <numDStateRecs>3</numDStateRecs>
    <numDataInputPorts>0</numDataInputPorts>
    <numLoggableCStateRecs>1</numLoggableCStateRecs>
    <numLoggableDStateRecs>3</numLoggableDStateRecs>
    <numLoggableJacobianDStates>3</numLoggableJacobianDStates>
    <runtimeNonFcnCallRateInfos type="ModelRefInfoRepo.RateInfo">
      <compiled>true</compiled>
      <period>0.0</period>
      <priority>40</priority>
      <rateIdx>0</rateIdx>
    </runtimeNonFcnCallRateInfos>
    <runtimeNonFcnCallRateInfos type="ModelRefInfoRepo.RateInfo">
      <compiled>true</compiled>
      <nonFcnCallPartitionName>Cont</nonFcnCallPartitionName>
      <period>.001</period>
      <priority>40</priority>
      <rateIdx>1</rateIdx>
    </runtimeNonFcnCallRateInfos>
    <sampleTimeInheritanceRule>2</sampleTimeInheritanceRule>
    <solverStatusFlags>331</solverStatusFlags>
    <timingAndTaskingRegistry>&lt;?xml version=&quot;1.0&quot;?&gt;
&lt;slexec_sto version=&quot;1.1&quot; packageUris=&quot;http://schema.mathworks.com/mf0/slexec_mm_sto/R2022b_202202091112&quot;&gt;
  &lt;sto.Registry type=&quot;sto.Registry&quot; uuid=&quot;c8968b95-9f07-4890-9fb3-8fa433204625&quot;&gt;
    &lt;executionSpec&gt;Undetermined&lt;/executionSpec&gt;
    &lt;clockRegistry type=&quot;sto.ClockRegistry&quot; uuid=&quot;73083237-bda1-4190-86cf-d685836c5a7b&quot;&gt;
      &lt;clocks type=&quot;sto.Timer&quot; uuid=&quot;9bd3e444-aeb3-40a8-9ed4-340931bf5ef0&quot;&gt;
        &lt;clockTickConstraint&gt;PeriodicWithFixedResolution&lt;/clockTickConstraint&gt;
        &lt;computedFundamentalDiscretePeriod&gt;.001&lt;/computedFundamentalDiscretePeriod&gt;
        &lt;resolution&gt;.001&lt;/resolution&gt;
        &lt;timeAdvanceMode&gt;FixedStep&lt;/timeAdvanceMode&gt;
        &lt;rates type=&quot;sto.ContinuousRate&quot; uuid=&quot;5f5eab3e-6849-48b3-9c98-6ce29fa5d588&quot;&gt;
          &lt;annotation&gt;Cont&lt;/annotation&gt;
          &lt;description&gt;Continuous&lt;/description&gt;
          &lt;taskId&gt;_task0&lt;/taskId&gt;
          &lt;rateSpec type=&quot;sto.RateSpec&quot; uuid=&quot;d4315ee1-7f61-47d4-80fb-012901f883c9&quot;/&gt;
        &lt;/rates&gt;
        &lt;rates type=&quot;sto.ClassicPeriodicDiscreteRate&quot; uuid=&quot;c1b838f8-1ef0-4ae3-aa79-feba35b52010&quot;&gt;
          &lt;annotation&gt;D1&lt;/annotation&gt;
          &lt;colorIndex&gt;2&lt;/colorIndex&gt;
          &lt;description&gt;Discrete 1&lt;/description&gt;
          &lt;rateIdx&gt;1&lt;/rateIdx&gt;
          &lt;taskId&gt;_task0&lt;/taskId&gt;
          &lt;rateSpec type=&quot;sto.RateSpec&quot; uuid=&quot;b52dfa7c-55fc-4a1d-b19b-1c72fbc4cfb4&quot;&gt;
            &lt;period&gt;.001&lt;/period&gt;
            &lt;rateType&gt;ClassicPeriodicDiscrete&lt;/rateType&gt;
          &lt;/rateSpec&gt;
        &lt;/rates&gt;
        &lt;baseRate type=&quot;sto.ContinuousRate&quot; uuid=&quot;c0416eda-3f15-44d4-a7ba-142c8f449f7f&quot;&gt;
          &lt;annotation&gt;Cont&lt;/annotation&gt;
          &lt;description&gt;Continuous&lt;/description&gt;
          &lt;taskId&gt;_task0&lt;/taskId&gt;
          &lt;rateSpec type=&quot;sto.RateSpec&quot; uuid=&quot;c3611bcf-929e-4691-b5f2-f6f872e9e842&quot;/&gt;
        &lt;/baseRate&gt;
      &lt;/clocks&gt;
      &lt;timeAdvanceMode&gt;FixedStep&lt;/timeAdvanceMode&gt;
    &lt;/clockRegistry&gt;
    &lt;taskRegistry type=&quot;sto.TaskRegistry&quot; uuid=&quot;b0cb0b89-001a-4136-8253-fa09c4de69bc&quot;&gt;
      &lt;rootTaskHierarchyElements type=&quot;sto.Task&quot; uuid=&quot;a10a65ed-71ea-4f65-a5c9-4f7e3a73708b&quot;&gt;
        &lt;isExecutable&gt;true&lt;/isExecutable&gt;
        &lt;orderIndex&gt;1&lt;/orderIndex&gt;
        &lt;rates type=&quot;sto.ContinuousRate&quot; uuid=&quot;ec53236a-ec56-4436-8793-1493656c8e00&quot;&gt;
          &lt;annotation&gt;Cont&lt;/annotation&gt;
          &lt;description&gt;Continuous&lt;/description&gt;
          &lt;taskId&gt;_task0&lt;/taskId&gt;
          &lt;rateSpec type=&quot;sto.RateSpec&quot; uuid=&quot;8c7f9f0a-059f-4407-9eef-5f7ac804c8c8&quot;/&gt;
        &lt;/rates&gt;
        &lt;rates type=&quot;sto.ClassicPeriodicDiscreteRate&quot; uuid=&quot;f867e229-634b-4ebd-bc9f-7714e151738b&quot;&gt;
          &lt;annotation&gt;D1&lt;/annotation&gt;
          &lt;colorIndex&gt;2&lt;/colorIndex&gt;
          &lt;description&gt;Discrete 1&lt;/description&gt;
          &lt;rateIdx&gt;1&lt;/rateIdx&gt;
          &lt;taskId&gt;_task0&lt;/taskId&gt;
          &lt;rateSpec type=&quot;sto.RateSpec&quot; uuid=&quot;23edbcf1-ac9e-4aad-b600-fd374f358408&quot;&gt;
            &lt;period&gt;.001&lt;/period&gt;
            &lt;rateType&gt;ClassicPeriodicDiscrete&lt;/rateType&gt;
          &lt;/rateSpec&gt;
        &lt;/rates&gt;
        &lt;elementType&gt;Task&lt;/elementType&gt;
        &lt;identifier&gt;_task0&lt;/identifier&gt;
        &lt;priority&gt;40&lt;/priority&gt;
      &lt;/rootTaskHierarchyElements&gt;
      &lt;taskDependencyGraph type=&quot;sto.SerializedTaskConnectionList&quot; uuid=&quot;ba2815ec-9998-4198-a6eb-7fc897f644c4&quot;&gt;
        &lt;taskIdentifier&gt;_task0&lt;/taskIdentifier&gt;
      &lt;/taskDependencyGraph&gt;
      &lt;taskPriorityDirection&gt;HighNumberLast&lt;/taskPriorityDirection&gt;
    &lt;/taskRegistry&gt;
  &lt;/sto.Registry&gt;
&lt;/slexec_sto&gt;</timingAndTaskingRegistry>
    <FMUBlockMap type="ModelRefInfoRepo.FMUBlockInfo" uuid="ee8b9c5d-0009-4fd1-8fff-9311e2694bc1"/>
    <codeGenInfo type="ModelRefInfoRepo.CodeGenInformation" uuid="9250a7e0-0d59-46c5-ba58-dffe42472daf"/>
    <compiledVariantInfos type="ModelRefInfoRepo.CompiledVariantInfoMap" uuid="a746e5fe-9ed0-4641-a558-7664811a6d3b"/>
    <configSettingsForConsistencyChecks type="ModelRefInfoRepo.ConfigSettingsForConsistencyChecks" uuid="beb71ace-e9e9-4c56-aeb8-1ea043afe177">
      <consistentOutportInitialization>true</consistentOutportInitialization>
      <fixedStepSize>.001</fixedStepSize>
      <frameDiagnosticSetting>2</frameDiagnosticSetting>
      <hasHybridSampleTime>true</hasHybridSampleTime>
      <signalLoggingSaveFormat>2</signalLoggingSaveFormat>
      <simSIMDOptimization>1</simSIMDOptimization>
      <solverName>ode5</solverName>
      <solverType>SOLVER_TYPE_FIXEDSTEP</solverType>
      <hardwareSettings type="ModelRefInfoRepo.HardwareSettings" uuid="1df4dc30-4a11-42e9-981c-78b652a88f0d">
        <prodBitPerChar>8</prodBitPerChar>
        <prodBitPerDouble>64</prodBitPerDouble>
        <prodBitPerFloat>32</prodBitPerFloat>
        <prodBitPerInt>32</prodBitPerInt>
        <prodBitPerLong>64</prodBitPerLong>
        <prodBitPerLongLong>64</prodBitPerLongLong>
        <prodBitPerPointer>64</prodBitPerPointer>
        <prodBitPerPtrDiffT>64</prodBitPerPtrDiffT>
        <prodBitPerShort>16</prodBitPerShort>
        <prodBitPerSizeT>64</prodBitPerSizeT>
        <prodEndianess>1</prodEndianess>
        <prodShiftRight>true</prodShiftRight>
        <prodWordSize>64</prodWordSize>
      </hardwareSettings>
    </configSettingsForConsistencyChecks>
    <controllableInputRatesMap type="ModelRefInfoRepo.VarTsUIDMap" uuid="9de31ad9-6d46-4e2f-ab6a-ea1c34bf77da"/>
    <controllableOutputRatesMap type="ModelRefInfoRepo.VarTsUIDMap" uuid="412d80da-9c26-408f-b94a-de4dd0c86b06"/>
    <dataPortGroup type="ModelRefInfoRepo.DataPortGroup" uuid="4d4ebb10-b928-4c4c-a890-b571607356a2"/>
    <expFcnUnconnectedDataPortGroup type="ModelRefInfoRepo.DataPortGroup" uuid="2c353460-3f77-4038-9c80-93fe2dc85b4d"/>
    <interfaceParameterInfo type="ModelRefInfoRepo.InterfaceParameterInfo" uuid="b2554406-d0da-44e8-8dbe-3c14eb7a3e93">
      <globalVariables type="ModelRefInfoRepo.BuiltinParameter" uuid="6e426070-69b9-40aa-aa94-abc2c43b6c68">
        <dimensions>6</dimensions>
        <dimensions>6</dimensions>
        <isUsed>true</isUsed>
        <numDimensions>2</numDimensions>
        <parameterName>Gromit_Cal_tranp</parameterName>
      </globalVariables>
      <globalVariables type="ModelRefInfoRepo.BuiltinParameter" uuid="0f2c9e44-1c96-4a51-9a2f-f4a72c861c8b">
        <dimensions>1</dimensions>
        <dimensions>1</dimensions>
        <isUsed>true</isUsed>
        <numDimensions>2</numDimensions>
        <parameterName>M</parameterName>
      </globalVariables>
      <globalVariables type="ModelRefInfoRepo.BuiltinParameter" uuid="0c47ff27-736d-4dbd-8caa-9f22cd4e5291">
        <dimensions>1</dimensions>
        <dimensions>1</dimensions>
        <isUsed>true</isUsed>
        <numDimensions>2</numDimensions>
        <parameterName>c</parameterName>
      </globalVariables>
      <globalVariables type="ModelRefInfoRepo.BuiltinParameter" uuid="95cadbab-06e5-4e11-90bb-4eab2a5f09b7">
        <dimensions>1</dimensions>
        <dimensions>1</dimensions>
        <isUsed>true</isUsed>
        <numDimensions>2</numDimensions>
        <parameterName>k</parameterName>
      </globalVariables>
      <globalVariables type="ModelRefInfoRepo.BuiltinParameter" uuid="db5bc64e-a41b-44b5-9635-8b429b1a29d6">
        <dimensions>1</dimensions>
        <dimensions>1</dimensions>
        <isUsed>true</isUsed>
        <numDimensions>2</numDimensions>
        <parameterName>start_position_cm</parameterName>
      </globalVariables>
    </interfaceParameterInfo>
    <messageInfo type="ModelRefInfoRepo.MessageInformation" uuid="1ba43248-d7f1-4cad-b2c3-911d8bb61706"/>
    <methodInfo type="ModelRefInfoRepo.MethodExistenceInfo" uuid="da5211d3-2826-4a8e-b58d-9920d8d28d0a">
      <hasDerivMethod>true</hasDerivMethod>
      <hasDisableMethod>true</hasDisableMethod>
      <hasEnableMethod>true</hasEnableMethod>
      <hasForcingFunctionMethod>true</hasForcingFunctionMethod>
      <hasSystemInitializeMethod>true</hasSystemInitializeMethod>
      <hasSystemResetMethod>true</hasSystemResetMethod>
      <hasTerminateMethod>true</hasTerminateMethod>
      <hasUpdateMethod>true</hasUpdateMethod>
    </methodInfo>
    <periodicEventPortUnsupportedBlockInfo type="ModelRefInfoRepo.PeriodicEventPortUnsupportedBlockInfo" uuid="fb15e553-d239-4b96-bc0f-953193370e02"/>
    <portGroupsRequireSameRate type="ModelRefInfoRepo.PortGroupsRequireSameRate" uuid="ee98a4f7-2684-464d-aaa5-81ce6ffd21c7">
      <DSMPortGroups type="ModelRefInfoRepo.NameToPortGroupIdxVectMap" uuid="e7b4d5e7-9da3-44b4-8967-d6b69e2bad6b"/>
      <GlobalDSMPortGroups type="ModelRefInfoRepo.NameToPortGroupIdxVectMap" uuid="3d3c1868-eee7-4779-9ec9-aa903d7bbdc7"/>
      <mergedPortGroups type="ModelRefInfoRepo.NameToPortGroupIdxVectMap" uuid="91b378c4-1e55-47ac-9452-4ae5e2d307ba"/>
    </portGroupsRequireSameRate>
    <rateBasedMdlGlobalDSMRateSpec type="ModelRefInfoRepo.GlobalDSMRateSpecMap" uuid="54606f3a-fce0-4344-8e27-e7fea431da29"/>
    <rateSpecOfGlobalDSMAccessedByDescExpFcnMdlMap type="ModelRefInfoRepo.GlobalDSMRateSpecMap" uuid="ae94b231-b41c-47ec-abde-50c2b69738ba"/>
    <rootBlockDiagramInterface type="ci.Model" uuid="8db676f7-5aa5-4bc6-82f1-e04bc5935c7f">
      <p_RootComponentInterface type="ci.ComponentInterface" uuid="a80d0beb-e901-4b23-a27c-bb5f246c1b3c">
        <p_Name>CPS_Eva</p_Name>
        <p_Type>ROOT</p_Type>
      </p_RootComponentInterface>
    </rootBlockDiagramInterface>
    <simulinkFunctions type="ModelRefInfoRepo.SimulinkFunctions" uuid="df24da5d-8bc5-491f-b4a0-426ad2910968">
      <compSimulinkFunctionCatalog></compSimulinkFunctionCatalog>
    </simulinkFunctions>
    <sltpContext type="sltp.mm.core.Context" uuid="6d47f504-91c5-455d-a591-cacb1b766f9c">
      <priorityDirection>HighNumberLast</priorityDirection>
      <editorState type="sltp.mm.core.EditorState" uuid="c10c48b9-050a-4c2e-9625-e1abca4feaad">
        <isSynchronized>true</isSynchronized>
        <panelState type="sltp.mm.core.EditorPanelState" uuid="5201ec29-d860-4a9c-91ad-6517356a39e8"/>
      </editorState>
      <rootTask type="sltp.mm.core.Task" uuid="cac9fd91-c3de-435b-ba8e-f9e87b004714">
        <context type="sltp.mm.core.Context" uuid="6d47f504-91c5-455d-a591-cacb1b766f9c"/>
        <explicit>false</explicit>
        <name>Default</name>
        <priority>-2147483648</priority>
        <subgraph type="sltp.mm.core.Graph" uuid="ff52b953-d4ae-4981-96d9-49772f8e51a9">
          <tasks type="sltp.mm.core.Task" uuid="79fada98-7123-4cee-ad11-e353f08ca141">
            <baseTask>true</baseTask>
            <context type="sltp.mm.core.Context" uuid="6d47f504-91c5-455d-a591-cacb1b766f9c"/>
            <explicit>false</explicit>
            <id>1</id>
            <isTimed>true</isTimed>
            <name>Cont</name>
            <priority>40</priority>
            <rates type="sltp.mm.core.Rate" uuid="bd5639cf-8751-4fef-94c7-f7e2229080c2">
              <annotation>Cont</annotation>
              <color>255</color>
              <hasBlocks>true</hasBlocks>
              <identifier>Continuous00</identifier>
              <rateSpec type="sltp.mm.core.RateSpec">
                <period>0.0</period>
              </rateSpec>
              <sti>0</sti>
            </rates>
            <rates type="sltp.mm.core.Rate" uuid="fa24458f-f66c-48ea-828e-56fd492140e1">
              <annotation>D1</annotation>
              <color>-436207361</color>
              <hasBlocks>true</hasBlocks>
              <rateSpec type="sltp.mm.core.RateSpec">
                <period>.001</period>
              </rateSpec>
              <sti>1</sti>
            </rates>
          </tasks>
        </subgraph>
      </rootTask>
    </sltpContext>
    <stateWriterToOwnerMap type="ModelRefInfoRepo.StateWriterInfo" uuid="1784ab4f-a50c-4073-ac20-4e7c58e89c43"/>
    <stoClientDataRegistry type="sto.ClientDataRegistry" uuid="970eca02-e2ef-480a-bcad-f3987b832265">
      <dataSets type="sto.ClientClockNamedDataSet" uuid="b2e33d5c-aa51-474c-8204-a8f6c6797cdb">
        <tag>sltpEvents</tag>
      </dataSets>
      <dataSets type="sto.ClientTaskHierarchyElementNamedDataSet" uuid="247b385a-8bae-40d7-94f2-e47d133dddea">
        <tag>sltpTaskGroups</tag>
      </dataSets>
      <dataSets type="sto.ClientTaskHierarchyElementNamedDataSet" uuid="1d51734b-7182-450b-b848-78b18bf5550c">
        <dSet type="ModelRefInfoRepo.SltpTaskData" uuid="88995d35-d490-49e6-af4c-f3db3f73d657"/>
        <tSet type="ModelRefInfoRepo.SltpTaskData" uuid="88995d35-d490-49e6-af4c-f3db3f73d657">
          <dataName>Cont</dataName>
          <linkedSet type="sto.ClientTaskHierarchyElementNamedDataSet" uuid="1d51734b-7182-450b-b848-78b18bf5550c"/>
          <id type="sto.TaskHierarchyElementId">
            <id>_task0</id>
          </id>
        </tSet>
        <tag>sltpTasks</tag>
      </dataSets>
    </stoClientDataRegistry>
    <varTsUIDMap type="ModelRefInfoRepo.VarTsUIDMap" uuid="ca37209f-a355-447e-8192-78645ae48660"/>
  </ModelRefInfoRepo.ModelRefInfoRoot>
</MF0>